ZetcodeRubyJiaochengChuyi/README.md
ZetcodeRubyJiaochengChuyi/__init__.py
ZetcodeRubyJiaochengChuyi/__main__.py
ZetcodeRubyJiaochengChuyi/file.epub
ZetcodeRubyJiaochengChuyi/index.html
ZetcodeRubyJiaochengChuyi/css/__init__.py
ZetcodeRubyJiaochengChuyi/css/annotations.css
ZetcodeRubyJiaochengChuyi/css/main.css
ZetcodeRubyJiaochengChuyi/css/normalize.css
ZetcodeRubyJiaochengChuyi/css/popup.css
ZetcodeRubyJiaochengChuyi/font/__init__.py
ZetcodeRubyJiaochengChuyi/font/fontello.eot
ZetcodeRubyJiaochengChuyi/font/fontello.svg
ZetcodeRubyJiaochengChuyi/font/fontello.ttf
ZetcodeRubyJiaochengChuyi/font/fontello.woff
ZetcodeRubyJiaochengChuyi/img/__init__.py
ZetcodeRubyJiaochengChuyi/img/annotator-glyph-sprite.png
ZetcodeRubyJiaochengChuyi/img/annotator-icon-sprite.png
ZetcodeRubyJiaochengChuyi/img/apple-touch-icon.png
ZetcodeRubyJiaochengChuyi/img/cancelfullscreen.png
ZetcodeRubyJiaochengChuyi/img/close.png
ZetcodeRubyJiaochengChuyi/img/fullscreen.png
ZetcodeRubyJiaochengChuyi/img/loader.gif
ZetcodeRubyJiaochengChuyi/img/menu-icon.png
ZetcodeRubyJiaochengChuyi/img/save.png
ZetcodeRubyJiaochengChuyi/img/saved.png
ZetcodeRubyJiaochengChuyi/img/settings-s.png
ZetcodeRubyJiaochengChuyi/img/settings.png
ZetcodeRubyJiaochengChuyi/img/star.png
ZetcodeRubyJiaochengChuyi/js/__init__.py
ZetcodeRubyJiaochengChuyi/js/epub.js
ZetcodeRubyJiaochengChuyi/js/epub.min.js
ZetcodeRubyJiaochengChuyi/js/epub.min.map
ZetcodeRubyJiaochengChuyi/js/hooks.min.js
ZetcodeRubyJiaochengChuyi/js/hooks.min.map
ZetcodeRubyJiaochengChuyi/js/reader.js
ZetcodeRubyJiaochengChuyi/js/reader.js.map
ZetcodeRubyJiaochengChuyi/js/reader.min.js
ZetcodeRubyJiaochengChuyi/js/reader.min.map
ZetcodeRubyJiaochengChuyi/js/hooks/__init__.py
ZetcodeRubyJiaochengChuyi/js/hooks/extensions/__init__.py
ZetcodeRubyJiaochengChuyi/js/hooks/extensions/highlight.js
ZetcodeRubyJiaochengChuyi/js/libs/__init__.py
ZetcodeRubyJiaochengChuyi/js/libs/jquery.min.js
ZetcodeRubyJiaochengChuyi/js/libs/localforage.min.js
zetcode_ruby_jiaocheng_chuyi-2024.3.5.0.dist-info/METADATA
zetcode_ruby_jiaocheng_chuyi-2024.3.5.0.dist-info/WHEEL
zetcode_ruby_jiaocheng_chuyi-2024.3.5.0.dist-info/entry_points.txt
zetcode_ruby_jiaocheng_chuyi-2024.3.5.0.dist-info/top_level.txt
zetcode_ruby_jiaocheng_chuyi-2024.3.5.0.dist-info/RECORD
